komorebic/__init__.py
komorebic/async_client.py
komorebic/base.py
komorebic/client.py
komorebic/event_manager.py
komorebic/events.py
komorebic/sync_client.py
komorebic/utils.py
komorebicpy-0.0.2.dist-info/METADATA
komorebicpy-0.0.2.dist-info/WHEEL
komorebicpy-0.0.2.dist-info/RECORD
